mpl_arrow/__init__.py
mpl_arrow/_arrow.py
mpl_arrow-0.1.0.dist-info/METADATA
mpl_arrow-0.1.0.dist-info/WHEEL
mpl_arrow-0.1.0.dist-info/licenses/LICENSE
mpl_arrow-0.1.0.dist-info/RECORD
