Metadata-Version: 2.1
Name: mpl-arrow
Version: 0.1.0
Summary: Easily plot nice-looking arrows with matplotlib
Project-URL: homepage, https://github.com/mpl-extensions/mpl-arrow
Project-URL: repository, https://github.com/mpl-extensions/mpl-arrow
Author-email: "Kevin M. Dalton" <kevinmdalton@gmail.com>, Ian Hunt-Isaak <ianhuntisaak@gmail.com>
License: MIT
License-File: LICENSE
Classifier: Development Status :: 3 - Alpha
Classifier: License :: OSI Approved :: BSD License
Classifier: Programming Language :: Python :: 3
Classifier: Programming Language :: Python :: 3.8
Classifier: Programming Language :: Python :: 3.9
Classifier: Programming Language :: Python :: 3.10
Requires-Python: >=3.8
Requires-Dist: matplotlib
Provides-Extra: dev
Requires-Dist: black; extra == 'dev'
Requires-Dist: ipython; extra == 'dev'
Requires-Dist: mypy; extra == 'dev'
Requires-Dist: pdbpp; extra == 'dev'
Requires-Dist: pre-commit; extra == 'dev'
Requires-Dist: pytest; extra == 'dev'
Requires-Dist: pytest-cov; extra == 'dev'
Requires-Dist: rich; extra == 'dev'
Requires-Dist: ruff; extra == 'dev'
Provides-Extra: doc
Requires-Dist: autoapi; extra == 'doc'
Requires-Dist: furo; extra == 'doc'
Requires-Dist: myst-nb; extra == 'doc'
Requires-Dist: numpydoc; extra == 'doc'
Requires-Dist: sphinx; extra == 'doc'
Requires-Dist: sphinx-autobuild; extra == 'doc'
Requires-Dist: sphinx-copybutton; extra == 'doc'
Provides-Extra: test
Requires-Dist: pytest-cov; extra == 'test'
Requires-Dist: pytest>=6.0; extra == 'test'
